Hibernate54ZhongwenWendang/README.md
Hibernate54ZhongwenWendang/__init__.py
Hibernate54ZhongwenWendang/__main__.py
Hibernate54ZhongwenWendang/file.epub
Hibernate54ZhongwenWendang/index.html
Hibernate54ZhongwenWendang/css/__init__.py
Hibernate54ZhongwenWendang/css/annotations.css
Hibernate54ZhongwenWendang/css/main.css
Hibernate54ZhongwenWendang/css/normalize.css
Hibernate54ZhongwenWendang/css/popup.css
Hibernate54ZhongwenWendang/font/__init__.py
Hibernate54ZhongwenWendang/font/fontello.eot
Hibernate54ZhongwenWendang/font/fontello.svg
Hibernate54ZhongwenWendang/font/fontello.ttf
Hibernate54ZhongwenWendang/font/fontello.woff
Hibernate54ZhongwenWendang/img/__init__.py
Hibernate54ZhongwenWendang/img/annotator-glyph-sprite.png
Hibernate54ZhongwenWendang/img/annotator-icon-sprite.png
Hibernate54ZhongwenWendang/img/apple-touch-icon.png
Hibernate54ZhongwenWendang/img/cancelfullscreen.png
Hibernate54ZhongwenWendang/img/close.png
Hibernate54ZhongwenWendang/img/fullscreen.png
Hibernate54ZhongwenWendang/img/loader.gif
Hibernate54ZhongwenWendang/img/menu-icon.png
Hibernate54ZhongwenWendang/img/save.png
Hibernate54ZhongwenWendang/img/saved.png
Hibernate54ZhongwenWendang/img/settings-s.png
Hibernate54ZhongwenWendang/img/settings.png
Hibernate54ZhongwenWendang/img/star.png
Hibernate54ZhongwenWendang/js/__init__.py
Hibernate54ZhongwenWendang/js/epub.js
Hibernate54ZhongwenWendang/js/epub.min.js
Hibernate54ZhongwenWendang/js/epub.min.map
Hibernate54ZhongwenWendang/js/hooks.min.js
Hibernate54ZhongwenWendang/js/hooks.min.map
Hibernate54ZhongwenWendang/js/reader.js
Hibernate54ZhongwenWendang/js/reader.js.map
Hibernate54ZhongwenWendang/js/reader.min.js
Hibernate54ZhongwenWendang/js/reader.min.map
Hibernate54ZhongwenWendang/js/hooks/__init__.py
Hibernate54ZhongwenWendang/js/hooks/extensions/__init__.py
Hibernate54ZhongwenWendang/js/hooks/extensions/highlight.js
Hibernate54ZhongwenWendang/js/libs/__init__.py
Hibernate54ZhongwenWendang/js/libs/jquery.min.js
hibernate_5_4_zhongwen_wendang-2024.3.4.0.dist-info/METADATA
hibernate_5_4_zhongwen_wendang-2024.3.4.0.dist-info/WHEEL
hibernate_5_4_zhongwen_wendang-2024.3.4.0.dist-info/entry_points.txt
hibernate_5_4_zhongwen_wendang-2024.3.4.0.dist-info/top_level.txt
hibernate_5_4_zhongwen_wendang-2024.3.4.0.dist-info/RECORD
